ringcentral_engage_voice/__init__.py
ringcentral_engage_voice/engage_voice_client.py
ringcentral_engage_voice-0.3.2.dist-info/LICENSE
ringcentral_engage_voice-0.3.2.dist-info/METADATA
ringcentral_engage_voice-0.3.2.dist-info/WHEEL
ringcentral_engage_voice-0.3.2.dist-info/top_level.txt
ringcentral_engage_voice-0.3.2.dist-info/RECORD
