Metadata-Version: 2.1
Name: ringcentral-engage-voice
Version: 0.3.2
Summary: RingCentral Engage Voice client Python
Home-page: https://github.com/ringcentral/engage-digital-python
Author: Drake Zhao @ RingCentral
Author-email: drake.zhao@ringcentral.com
License: UNKNOWN
Keywords: RingCentral,Engage Digital,sdk
Platform: UNKNOWN
Classifier: Programming Language :: Python :: 3
Classifier: Programming Language :: Python :: 2
Classifier: License :: OSI Approved :: MIT License
Classifier: Operating System :: OS Independent
Requires-Dist: requests
Requires-Dist: pydash
Requires-Dist: ringcentral
